Metadata-Version: 2.1
Name: mccolor
Version: 1.0.0
Summary: Simple library to use minecraft color codes in terminal
Home-page: https://github.com/wrrulos/mccolor
Author: wrrulos
Author-email: vegapedro2004@gmail.com
Keywords: color,colour,paint,ansi,terminal,linux,python,python3,minecraft
Classifier: Environment :: Console
Classifier: License :: OSI Approved :: MIT License
Classifier: Operating System :: Microsoft :: Windows
Classifier: Operating System :: POSIX
Classifier: Operating System :: POSIX :: Linux
Classifier: Operating System :: POSIX :: Other
Classifier: Operating System :: OS Independent
Classifier: Programming Language :: Python :: 3
Classifier: Topic :: Terminals
